MANIFEST.in
README.txt
setup.cfg
setup.py
atreal/__init__.py
atreal.override.albumview.egg-info/PKG-INFO
atreal.override.albumview.egg-info/SOURCES.txt
atreal.override.albumview.egg-info/dependency_links.txt
atreal.override.albumview.egg-info/entry_points.txt
atreal.override.albumview.egg-info/namespace_packages.txt
atreal.override.albumview.egg-info/not-zip-safe
atreal.override.albumview.egg-info/requires.txt
atreal.override.albumview.egg-info/top_level.txt
atreal/override/__init__.py
atreal/override/albumview/__init__.py
atreal/override/albumview/configure.zcml
atreal/override/albumview/interfaces.py
atreal/override/albumview/browser/__init__.py
atreal/override/albumview/browser/configure.zcml
atreal/override/albumview/browser/search.pt
atreal/override/albumview/browser/view.pt
atreal/override/albumview/browser/view.py
atreal/override/albumview/profiles/default/browserlayer.xml
atreal/override/albumview/profiles/default/componentregistry.xml
atreal/override/albumview/profiles/default/metadata.xml
atreal/override/albumview/profiles/default/skins.xml
atreal/override/albumview/skins/atreal_override_albumview/application.png
atreal/override/albumview/skins/atreal_override_albumview/audio.png
atreal/override/albumview/skins/atreal_override_albumview/avi.png
atreal/override/albumview/skins/atreal_override_albumview/c.png
atreal/override/albumview/skins/atreal_override_albumview/core.png
atreal/override/albumview/skins/atreal_override_albumview/cpp.png
atreal/override/albumview/skins/atreal_override_albumview/deb.png
atreal/override/albumview/skins/atreal_override_albumview/doc.png
atreal/override/albumview/skins/atreal_override_albumview/document_icon.gif
atreal/override/albumview/skins/atreal_override_albumview/down.png
atreal/override/albumview/skins/atreal_override_albumview/dvi.png
atreal/override/albumview/skins/atreal_override_albumview/event_icon.gif
atreal/override/albumview/skins/atreal_override_albumview/exe.png
atreal/override/albumview/skins/atreal_override_albumview/f.png
atreal/override/albumview/skins/atreal_override_albumview/file_icon.gif
atreal/override/albumview/skins/atreal_override_albumview/folder_icon.gif
atreal/override/albumview/skins/atreal_override_albumview/font.png
atreal/override/albumview/skins/atreal_override_albumview/gf.png
atreal/override/albumview/skins/atreal_override_albumview/h.png
