Metadata-Version: 1.1
Name: atreal.override.albumview
Version: 1.0.0rc2
Summary: Override album view of Plone for FileCart or/and RichFile Packages
Home-page: http://www.atreal.net
Author: atReal
Author-email: contact@atreal.net
License: GPL
Platform: UNKNOWN
Classifier: Framework :: Plone
Classifier: Programming Language :: Python
Classifier: Topic :: Software Development :: Libraries :: Python Modules
